knowledge_graph/__init__.py
knowledge_graph/common_relations.py
knowledge_graph/minigraph_builders.py
knowledge_graph/primitives.py
knowledge_graph/querying.py
knowledge_graph/querying_raw.py
knowledge_graph/querying_raw_test.py
knowledge_graph/storage.py
knowledge_graph/transform.py
knowledge_graph/transform_test.py
knowledge_graph/triplet.py
knowledge_graph/triplets_index.py
knowledge_graph-0.0.33.dist-info/licenses/LICENSE
knowledge_graph-0.0.33.dist-info/METADATA
knowledge_graph-0.0.33.dist-info/WHEEL
knowledge_graph-0.0.33.dist-info/top_level.txt
knowledge_graph-0.0.33.dist-info/RECORD
