Metadata-Version: 2.4
Name: knowledge-graph
Version: 0.0.33
Summary: A library to store data in a knowledge graph
Home-page: https://github.com/hyroai/knowledge-graph/
Author: Hyro AI
Author-email: contact@hyro.ai
Keywords: tag1,tag2
Requires-Python: >=3.11
License-File: LICENSE
Requires-Dist: dataclasses_json==0.5.7
Requires-Dist: immutables
Requires-Dist: pytest
Requires-Dist: phonenumbers
Dynamic: author
Dynamic: author-email
Dynamic: description
Dynamic: description-content-type
Dynamic: home-page
Dynamic: keywords
Dynamic: license-file
Dynamic: requires-dist
Dynamic: requires-python
Dynamic: summary
